fourth_day/__init__.py
fourth_day/adamah.py
fourth_day/config.py
fourth_day/current.py
fourth_day/fourth_day.py
fourth_day/functions.py
fourth_day/genesis.py
fourth_day/lucifer.py
fourth_day/mc_sim.py
fourth_day/pdfs.py
fourth_day/providence.py
fourth_day/state_machine.py
fourth_day/vtu_npy_handlers.py
fourth_day/data/life/light/Cnidaria_Hydrozoa.txt
fourth_day/data/life/light/Cnidaria_Hydrozoa_Hydroidolina_Siphonophores_Calycophorae.txt
fourth_day/data/life/light/Cnidaria_Hydrozoa_Hydroidolina_Siphonophores_Physonectae.txt
fourth_day/data/life/light/Cnidaria_Scyphomedusae.txt
fourth_day/data/life/light/Ctenophores.txt
fourth_day/data/life/light/Proteobacteria_Gammaproteobacteria.txt
fourth_day/data/life/movement/Annelida.txt
fourth_day/data/life/movement/Arthropoda.txt
fourth_day/data/life/movement/Chordata.txt
fourth_day/data/life/movement/Dinoflagellata.txt
fourth_day-1.0.12.dist-info/LICENSE.txt
fourth_day-1.0.12.dist-info/METADATA
fourth_day-1.0.12.dist-info/WHEEL
fourth_day-1.0.12.dist-info/top_level.txt
fourth_day-1.0.12.dist-info/RECORD
