Metadata-Version: 2.1
Name: fourth_day
Version: 1.0.12
Summary: Bioluminescence modeling for deep-sea experiments
Home-page: https://github.com/MeighenBergerS/fourth_day
Author: Stephan Meighen-Berger
Author-email: stephan.meighenberger@gmail.com
License: MIT
License-File: LICENSE.txt
Requires-Dist: pyyaml
Requires-Dist: numpy
Requires-Dist: scipy
Requires-Dist: pandas
Requires-Dist: pyDataverse >=0.3.0
Requires-Dist: tqdm >=4.0.0
Provides-Extra: interactive
Requires-Dist: nbstripout ; extra == 'interactive'
Requires-Dist: matplotlib ; extra == 'interactive'
Requires-Dist: jupyter ; extra == 'interactive'
